{
  "kanaStatus": {},
  "starred": {},
  "score": 0,
  "theme": "light",
  "kanaCustom": {
    "hiragana": [],
    "katakana": []
  },
  "customHiragana": [],
  "customKatakana": [],
  "kanaHidden": {
    "hiragana": [],
    "katakana": []
  },
  "kanjiGroups": [
    {
      "id": "chars",
      "title": "📝 Chữ Kanji",
      "note": "100 chữ Kanji cơ bản",
      "builtin": true
    },
    {
      "id": "radicals",
      "title": "🔑 Bộ thủ",
      "note": "83 bộ thủ cơ bản",
      "builtin": true
    },
    {
      "id": "grp_1784453912405",
      "title": "📚 moisw",
      "note": "",
      "icon": "📚",
      "items": [
        {
          "kana": "ggu",
          "romaji": "hfd",
          "meaning": "gf",
          "hanviet": "",
          "onyomi": "",
          "kunyomi": "",
          "example": "",
          "group": "custom"
        }
      ],
      "builtin": false
    }
  ],
  "kanjiCustomChars": [],
  "kanjiCustomRadicals": [],
  "lastSync": "2026-07-19T09:38:56.967Z"
}